{"cookies": [{"name": "sessionid", "value": "BgAAAF49A306%2BZXTPNOD8NWcslTni1y5Yd5rbk57LFPa7ef7Pz0phCkSQGKzd0tSrwWrTUU8e6fVq%2FJAAiRlE0vaJtoq0DYUVsu2KoVnA0Q%3D", "domain": "channels.weixin.qq.com", "path": "/", "expires": 1807753586.663472, "httpOnly": false, "secure": true, "sameSite": "None"}, {"name": "wxuin", "value": "2247032622", "domain": "channels.weixin.qq.com", "path": "/", "expires": 1807753586.663536, "httpOnly": false, "secure": true, "sameSite": "None"}], "origins": [{"origin": "https://channels.weixin.qq.com", "localStorage": [{"name": "finder_route_meta", "value": "micro.content/post/list;index;1;1773193599291"}, {"name": "__ml::hb_ts", "value": "1773193576807"}, {"name": "__ml::page_90bf107e-8dc7-4df0-af16-4f37a8453c48", "value": "{\"pageId\":\"LoginForIframe\",\"accessId\":\"e75bae67-04d4-44c7-9503-2567b55ea5a5\",\"step\":1}"}, {"name": "__ml::page_a74abce1-ba34-4561-af49-8ca41878b4e5", "value": "{\"pageId\":\"MicroPost\",\"accessId\":\"eb40f2d0-bb81-4c5a-9814-44b9e378e7cf\",\"step\":1}"}, {"name": "__rx::aid", "value": "\"64f343de-d72b-48fa-bbd2-86ae460b8a9c\""}, {"name": "__ml::aid", "value": "\"64f343de-d72b-48fa-bbd2-86ae460b8a9c\""}, {"name": "__ml::page", "value": "[\"90bf107e-8dc7-4df0-af16-4f37a8453c48\",\"d38330de-643b-47e9-b40e-63c3b3b294f5\",\"a74abce1-ba34-4561-af49-8ca41878b4e5\",\"a014ba09-1674-4c61-8252-72fbe0483884\"]"}, {"name": "finder_login_token", "value": ""}, {"name": "__ml::page_d38330de-643b-47e9-b40e-63c3b3b294f5", "value": "{\"pageId\":\"LoginForIframe\",\"accessId\":\"6995cc81-030d-45a1-a3b3-81a702f29890\",\"step\":1}"}, {"name": "finder_username", "value": "v2_060000231003b20faec8c5e48919cbd5cb05e53db077dd1924028a806c10cffd891eb5a80ce7@finder"}, {"name": "_finger_print_device_id", "value": "6fd704941768442b12a996d2652fc61e"}, {"name": "MICRO_VISITED_NAME", "value": "{\"content\":1}"}, {"name": "__ml::page_a014ba09-1674-4c61-8252-72fbe0483884", "value": "{\"pageId\":\"PostList\",\"accessId\":\"b9ab38d8-1f82-4bf3-96ca-1ce2d7ba2ec2\",\"step\":1}"}, {"name": "UvFirstReportLocalKey", "value": "1773158400000"}, {"name": "finder_ua_report_data", "value": "{\"browser\":\"Chrome\",\"browserVersion\":\"131.0.0.0\",\"engine\":\"Webkit\",\"engineVersion\":\"537.36\",\"os\":\"Mac OS X\",\"osVersion\":\"10.15.7\",\"device\":\"desktop\",\"darkmode\":0}"}, {"name": "finder_uin", "value": ""}]}]}